setup.py
test_distributions/Binomialdistribution.py
test_distributions/Gaussiandistribution.py
test_distributions/Generaldistribution.py
test_distributions/__init__.py
test_distributions.egg-info/PKG-INFO
test_distributions.egg-info/SOURCES.txt
test_distributions.egg-info/dependency_links.txt
test_distributions.egg-info/not-zip-safe
test_distributions.egg-info/top_level.txt